{
    "data": {
        "nabz_product_id": null,
        "business_card_slug": null,
        "seo": {
            "title": "بهجت آباد ۱۱۲ متر _ نوساز _ غرق نور _ خوش نقشه|اجارهٔ آپارتمان|تهران، بهجت‌آباد|دیوار",
            "description": "بهجت آباد ۱۱۲ متر _ نوساز _ غرق نور _ خوش نقشه|اجارهٔ آپارتمان|تهران، بهجت‌آباد|خرید و فروش ^^^  به نام خدا  ^^^\n\n\n\n*** توجه ***                         *** توجه ***\n\n /   واحد از هر نظر بی نقص و کامل میباشد /   \n\n*** توجه ***                         *** توجه ***\n\n\n\n\n***توجه ***                         *** توجه ***\n\n/ مهم ترین نکته قیمت  واحد و مالک منصف /\n\n***توجه ***                          *** توجه ***\n\n\n/   بهجت آباد \n/  خیابان سربداران\n/   دسترسی زیر ۵ دقیقه به مترو و اتوبانها\n/  ۱۱۲متر \n/   ۲خواب بزرگ و سرتاسر کمد \n/   بالکن بزرگ دارد \n/  واحد بدون ۱ سانت پرتی \n/   انباری بزرگ \n/   اسانسور \n/  پارکینگ بهترین نقطه \n/   طبقه پنجم و غرق نور \n/  سالن پرده خور و قابل چیدمان ۲ دست مبلمان\n/   مالک منصف\n/   امکان تمدید در سالهای آینده \n/   بدون حضور مالک در ساختمان\n/   مشاور و همراه شما عطایی \n/   لطفا در صورت در دسترس نبودن با شماره ثابت و داخلی عطایی تماس بگیرید ممنون| سایت ثبت آگهی، نیازمندی و خرید و فروش دیوار",
            "url": "https://divar.ir/v/%D8%A8%D9%87%D8%AC%D8%AA-%D8%A2%D8%A8%D8%A7%D8%AF-%DB%B1%DB%B1%DB%B2-%D9%85%D8%AA%D8%B1-%D9%86%D9%88%D8%B3%D8%A7%D8%B2-%D8%BA%D8%B1%D9%82-%D9%86%D9%88%D8%B1-%D8%AE%D9%88%D8%B4-%D9%86%D9%82%D8%B4%D9%87_اجارهٔ-آپارتمان_تهران_بهجت-آباد_دیوار/QZMQbn3j",
            "home_url": "https://divar.ir/tehran/تهران/browse",
            "android_package_name": "ir.divar",
            "ios_app_id": "863029557",
            "android_app_url": "android-app://ir.divar/http/v/بهجت آباد ۱۱۲ متر _ نوساز _ غرق نور _ خوش نقشه/QZMQbn3j/",
            "ios_app_url": "ios-app://863029557/http/v/بهجت آباد ۱۱۲ متر _ نوساز _ غرق نور _ خوش نقشه/QZMQbn3j/",
            "thumbnail": "https://s100.divarcdn.com/static/photo/thumbnail/CWalLZgSUlzDlHyLTAwIpw/84098672-a380-461b-bffb-d4acdb36a3a3.jpg"
        },
        "share": {
            "title": "بهجت آباد ۱۱۲ متر _ نوساز _ غرق نور _ خوش نقشه",
            "description": "^^^  به نام خدا  ^^^\n\n\n\n*** توجه ***                         *** توجه ***\n\n /   واحد از هر نظر بی نقص و کامل میباشد /   \n\n*** توجه ***                         *** توجه ***\n\n\n\n\n***توجه ***                         *** توجه ***\n\n/ مهم ترین نکته قیمت  واحد و مالک منصف /\n\n***توجه ***                          *** توجه ***\n\n\n/   بهجت آباد \n/  خیابان سربداران\n/   دسترسی زیر ۵ دقیقه به مترو و اتوبانها\n/  ۱۱۲متر \n/   ۲خواب بزرگ و سرتاسر کمد \n/   بالکن بزرگ دارد \n/  واحد بدون ۱ سانت پرتی \n/   انباری بزرگ \n/   اسانسور \n/  پارکینگ بهترین نقطه \n/   طبقه پنجم و غرق نور \n/  سالن پرده خور و قابل چیدمان ۲ دست مبلمان\n/   مالک منصف\n/   امکان تمدید در سالهای آینده \n/   بدون حضور مالک در ساختمان\n/   مشاور و همراه شما عطایی \n/   لطفا در صورت در دسترس نبودن با شماره ثابت و داخلی عطایی تماس بگیرید ممنون",
            "android_url": "https://divar.ir/v/QZMQbn3j?ref=android",
            "ios_url": "https://divar.ir/v/QZMQbn3j?ref=ios",
            "web_url": "https://divar.ir/v/QZMQbn3j"
        },
        "url": "https://divar.ir/v/%D8%A8%D9%87%D8%AC%D8%AA-%D8%A2%D8%A8%D8%A7%D8%AF-%DB%B1%DB%B1%DB%B2-%D9%85%D8%AA%D8%B1-%D9%86%D9%88%D8%B3%D8%A7%D8%B2-%D8%BA%D8%B1%D9%82-%D9%86%D9%88%D8%B1-%D8%AE%D9%88%D8%B4-%D9%86%D9%82%D8%B4%D9%87_اجارهٔ-آپارتمان_تهران_بهجت-آباد_دیوار/QZMQbn3j",
        "category": {
            "slug": "apartment-rent",
            "title": "اجارهٔ آپارتمان",
            "second_slug": "اجارهٔ آپارتمان"
        },
        "description": "^^^  به نام خدا  ^^^\n\n\n\n*** توجه ***                         *** توجه ***\n\n /   واحد از هر نظر بی نقص و کامل میباشد /   \n\n*** توجه ***                         *** توجه ***\n\n\n\n\n***توجه ***                         *** توجه ***\n\n/ مهم ترین نکته قیمت  واحد و مالک منصف /\n\n***توجه ***                          *** توجه ***\n\n\n/   بهجت آباد \n/  خیابان سربداران\n/   دسترسی زیر ۵ دقیقه به مترو و اتوبانها\n/  ۱۱۲متر \n/   ۲خواب بزرگ و سرتاسر کمد \n/   بالکن بزرگ دارد \n/  واحد بدون ۱ سانت پرتی \n/   انباری بزرگ \n/   اسانسور \n/  پارکینگ بهترین نقطه \n/   طبقه پنجم و غرق نور \n/  سالن پرده خور و قابل چیدمان ۲ دست مبلمان\n/   مالک منصف\n/   امکان تمدید در سالهای آینده \n/   بدون حضور مالک در ساختمان\n/   مشاور و همراه شما عطایی \n/   لطفا در صورت در دسترس نبودن با شماره ثابت و داخلی عطایی تماس بگیرید ممنون",
        "business_data": {
            "business_type": "real-estate-business",
            "business_ref": "agent_467174",
            "data": {
                "id": "467174",
                "name": "حمید عطایی دوست ",
                "slug": "uWNtJgVb",
                "score": 0.67762154,
                "usedFrom": "AGENT",
                "submitType": "INDEPENDENT_AGENT_SUBMIT"
            }
        },
        "city": "تهران",
        "webengage": {
            "category": "apartment-rent",
            "token": "QZMQbn3j",
            "city": "tehran",
            "brand_model": null,
            "image_count": 7,
            "district": "بهجت‌آباد",
            "cat_3": {
                "full_title": "اجاره آپارتمان",
                "icon_url": "",
                "old_meta_id": 214,
                "parent_slug": "residential-rent",
                "slug": "apartment-rent",
                "title": "اجارهٔ آپارتمان",
                "second_slug": "اجارهٔ آپارتمان",
                "relative_url": "tehran/rent-apartment"
            },
            "cat_2": {
                "full_title": "",
                "icon_url": "",
                "old_meta_id": 213,
                "parent_slug": "real-estate",
                "slug": "residential-rent",
                "title": "اجارهٔ مسکونی",
                "second_slug": "اجارهٔ مسکونی",
                "relative_url": "tehran/rent-residential"
            },
            "cat_1": {
                "full_title": "",
                "icon_url": "https://s100.divarcdn.com/static/explorers/categories/house_%s.png",
                "old_meta_id": 143,
                "parent_slug": "root",
                "slug": "real-estate",
                "title": "املاک",
                "second_slug": "املاک",
                "relative_url": "tehran/real-estate"
            },
            "status": "",
            "originality": "",
            "business_type": "real-estate-business",
            "business_ref": "agent_467174",
            "data": {
                "id": "467174",
                "name": "حمید عطایی دوست ",
                "slug": "uWNtJgVb",
                "score": 0.67762154,
                "usedFrom": "AGENT",
                "submitType": "INDEPENDENT_AGENT_SUBMIT"
            },
            "price": null,
            "rent": 25000000,
            "credit": 200000000
        },
        "district": "بهجت‌آباد",
        "brand_model": null
    },
    "widgets": {
        "header": {
            "date": "۷ ساعت پیش",
            "subtitle": "۷ ساعت پیش در تهران، بهجت‌آباد | اجاره آپارتمان",
            "title": "بهجت آباد ۱۱۲ متر / نوساز / غرق نور / خوش نقشه",
            "thumbnail": "https://s100.divarcdn.com/static/photo/thumbnail/CWalLZgSUlzDlHyLTAwIpw/84098672-a380-461b-bffb-d4acdb36a3a3.jpg",
            "place": "بهجت‌آباد",
            "business_logo": null
        },
        "description": "^^^  به نام خدا  ^^^\n\n\n\n*** توجه ***                         *** توجه ***\n\n /   واحد از هر نظر بی نقص و کامل میباشد /   \n\n*** توجه ***                         *** توجه ***\n\n\n\n\n***توجه ***                         *** توجه ***\n\n/ مهم ترین نکته قیمت  واحد و مالک منصف /\n\n***توجه ***                          *** توجه ***\n\n\n/   بهجت آباد \n/  خیابان سربداران\n/   دسترسی زیر ۵ دقیقه به مترو و اتوبانها\n/  ۱۱۲متر \n/   ۲خواب بزرگ و سرتاسر کمد \n/   بالکن بزرگ دارد \n/  واحد بدون ۱ سانت پرتی \n/   انباری بزرگ \n/   اسانسور \n/  پارکینگ بهترین نقطه \n/   طبقه پنجم و غرق نور \n/  سالن پرده خور و قابل چیدمان ۲ دست مبلمان\n/   مالک منصف\n/   امکان تمدید در سالهای آینده \n/   بدون حضور مالک در ساختمان\n/   مشاور و همراه شما عطایی \n/   لطفا در صورت در دسترس نبودن با شماره ثابت و داخلی عطایی تماس بگیرید ممنون",
        "description_show_lines": 0,
        "list_data": [
            {
                "format": "group_info_row",
                "title": "اطلاعات",
                "has_divider": true,
                "items": [
                    {
                        "title": "متراژ",
                        "value": "۱۱۲"
                    },
                    {
                        "title": "ساخت",
                        "value": "۱۳۹۸"
                    },
                    {
                        "title": "اتاق",
                        "value": "۲"
                    }
                ]
            },
            {
                "title": "ودیعه",
                "format": "string",
                "value": "۲۰۰٬۰۰۰٬۰۰۰ تومان"
            },
            {
                "title": "اجارهٔ ماهانه",
                "format": "string",
                "value": "۲۵٬۰۰۰٬۰۰۰ تومان"
            },
            {
                "title": "ودیعه و اجاره",
                "format": "string",
                "value": "غیر قابل تبدیل"
            },
            {
                "title": "مناسب برای",
                "format": "string",
                "value": "خانواده و مجرد"
            },
            {
                "title": "طبقه",
                "format": "string",
                "value": "۵ از ۵"
            },
            {
                "format": "group_feature_row",
                "title": "ویژگی‌ها و امکانات",
                "items": [
                    {
                        "title": "آسانسور",
                        "available": true,
                        "icon": {
                            "image_url_dark": "https://s100.divarcdn.com/static/imgs/widget-icons/dark/icon_secondary/elevator.png",
                            "image_url_light": "https://s100.divarcdn.com/static/imgs/widget-icons/light/icon_secondary/elevator.png",
                            "icon_name": "ELEVATOR",
                            "icon_color": "ICON_SECONDARY"
                        }
                    },
                    {
                        "title": "پارکینگ",
                        "available": true,
                        "icon": {
                            "image_url_dark": "https://s100.divarcdn.com/static/imgs/widget-icons/dark/icon_secondary/parking.png",
                            "image_url_light": "https://s100.divarcdn.com/static/imgs/widget-icons/light/icon_secondary/parking.png",
                            "icon_name": "PARKING",
                            "icon_color": "ICON_SECONDARY"
                        }
                    },
                    {
                        "title": "انباری",
                        "available": true,
                        "icon": {
                            "image_url_dark": "https://s100.divarcdn.com/static/imgs/widget-icons/dark/icon_secondary/cabinet.png",
                            "image_url_light": "https://s100.divarcdn.com/static/imgs/widget-icons/light/icon_secondary/cabinet.png",
                            "icon_name": "CABINET",
                            "icon_color": "ICON_SECONDARY"
                        }
                    }
                ],
                "has_divider": true,
                "next_page_text": "نمایش همهٔ جزئیات",
                "next_page": {
                    "title": "ویژگی‌ها و امکانات",
                    "widget_list": [
                        {
                            "widget_type": "TITLE_ROW",
                            "data": {
                                "@type": "type.googleapis.com/widgets.TitleRowData",
                                "text": "ویژگی‌ها",
                                "text_color": "TEXT_PRIMARY",
                                "has_divider": false,
                                "color": ""
                            },
                            "visibility_condition": []
                        },
                        {
                            "widget_type": "UNEXPANDABLE_ROW",
                            "data": {
                                "@type": "type.googleapis.com/widgets.UnexpandableRowData",
                                "title": "تعداد واحد در طبقه",
                                "value": "۲",
                                "has_divider": true,
                                "compact": false,
                                "has_copy_to_clipboard": false
                            },
                            "visibility_condition": []
                        },
                        {
                            "widget_type": "UNEXPANDABLE_ROW",
                            "data": {
                                "@type": "type.googleapis.com/widgets.UnexpandableRowData",
                                "title": "جهت ساختمان",
                                "value": "جنوبی",
                                "has_divider": true,
                                "compact": false,
                                "has_copy_to_clipboard": false
                            },
                            "visibility_condition": []
                        },
                        {
                            "widget_type": "TITLE_ROW",
                            "data": {
                                "@type": "type.googleapis.com/widgets.TitleRowData",
                                "text": "امکانات",
                                "text_color": "TEXT_PRIMARY",
                                "has_divider": false,
                                "color": ""
                            },
                            "visibility_condition": []
                        },
                        {
                            "widget_type": "FEATURE_ROW",
                            "data": {
                                "@type": "type.googleapis.com/widgets.FeatureRowData",
                                "title": "آسانسور",
                                "has_divider": true,
                                "icon": {
                                    "image_url_dark": "https://s100.divarcdn.com/static/imgs/widget-icons/dark/icon_secondary/elevator.png",
                                    "image_url_light": "https://s100.divarcdn.com/static/imgs/widget-icons/light/icon_secondary/elevator.png",
                                    "icon_name": "ELEVATOR",
                                    "icon_color": "ICON_SECONDARY"
                                },
                                "image_url": "",
                                "image_color": "UNKNOWN",
                                "disabled": false
                            },
                            "visibility_condition": []
                        },
                        {
                            "widget_type": "FEATURE_ROW",
                            "data": {
                                "@type": "type.googleapis.com/widgets.FeatureRowData",
                                "title": "پارکینگ",
                                "has_divider": true,
                                "icon": {
                                    "image_url_dark": "https://s100.divarcdn.com/static/imgs/widget-icons/dark/icon_secondary/parking.png",
                                    "image_url_light": "https://s100.divarcdn.com/static/imgs/widget-icons/light/icon_secondary/parking.png",
                                    "icon_name": "PARKING",
                                    "icon_color": "ICON_SECONDARY"
                                },
                                "image_url": "",
                                "image_color": "UNKNOWN",
                                "disabled": false
                            },
                            "visibility_condition": []
                        },
                        {
                            "widget_type": "FEATURE_ROW",
                            "data": {
                                "@type": "type.googleapis.com/widgets.FeatureRowData",
                                "title": "انباری",
                                "has_divider": true,
                                "icon": {
                                    "image_url_dark": "https://s100.divarcdn.com/static/imgs/widget-icons/dark/icon_secondary/cabinet.png",
                                    "image_url_light": "https://s100.divarcdn.com/static/imgs/widget-icons/light/icon_secondary/cabinet.png",
                                    "icon_name": "CABINET",
                                    "icon_color": "ICON_SECONDARY"
                                },
                                "image_url": "",
                                "image_color": "UNKNOWN",
                                "disabled": false
                            },
                            "visibility_condition": []
                        },
                        {
                            "widget_type": "FEATURE_ROW",
                            "data": {
                                "@type": "type.googleapis.com/widgets.FeatureRowData",
                                "title": "بالکن",
                                "has_divider": true,
                                "icon": {
                                    "image_url_dark": "https://s100.divarcdn.com/static/imgs/widget-icons/dark/icon_secondary/balcony.png",
                                    "image_url_light": "https://s100.divarcdn.com/static/imgs/widget-icons/light/icon_secondary/balcony.png",
                                    "icon_name": "BALCONY",
                                    "icon_color": "ICON_SECONDARY"
                                },
                                "image_url": "",
                                "image_color": "UNKNOWN",
                                "disabled": false
                            },
                            "visibility_condition": []
                        },
                        {
                            "widget_type": "FEATURE_ROW",
                            "data": {
                                "@type": "type.googleapis.com/widgets.FeatureRowData",
                                "title": "جنس کف سرامیک",
                                "has_divider": true,
                                "icon": {
                                    "image_url_dark": "https://s100.divarcdn.com/static/imgs/widget-icons/dark/icon_secondary/texture.png",
                                    "image_url_light": "https://s100.divarcdn.com/static/imgs/widget-icons/light/icon_secondary/texture.png",
                                    "icon_name": "TEXTURE",
                                    "icon_color": "ICON_SECONDARY"
                                },
                                "image_url": "",
                                "image_color": "UNKNOWN",
                                "disabled": false
                            },
                            "visibility_condition": []
                        },
                        {
                            "widget_type": "FEATURE_ROW",
                            "data": {
                                "@type": "type.googleapis.com/widgets.FeatureRowData",
                                "title": "سرویس بهداشتی ایرانی و فرنگی",
                                "has_divider": true,
                                "icon": {
                                    "image_url_dark": "https://s100.divarcdn.com/static/imgs/widget-icons/dark/icon_secondary/wc.png",
                                    "image_url_light": "https://s100.divarcdn.com/static/imgs/widget-icons/light/icon_secondary/wc.png",
                                    "icon_name": "WC",
                                    "icon_color": "ICON_SECONDARY"
                                },
                                "image_url": "",
                                "image_color": "UNKNOWN",
                                "disabled": false
                            },
                            "visibility_condition": []
                        },
                        {
                            "widget_type": "FEATURE_ROW",
                            "data": {
                                "@type": "type.googleapis.com/widgets.FeatureRowData",
                                "title": "سرمایش کولر آبی",
                                "has_divider": true,
                                "icon": {
                                    "image_url_dark": "https://s100.divarcdn.com/static/imgs/widget-icons/dark/icon_secondary/snowflake.png",
                                    "image_url_light": "https://s100.divarcdn.com/static/imgs/widget-icons/light/icon_secondary/snowflake.png",
                                    "icon_name": "SNOWFLAKE",
                                    "icon_color": "ICON_SECONDARY"
                                },
                                "image_url": "",
                                "image_color": "UNKNOWN",
                                "disabled": false
                            },
                            "visibility_condition": []
                        },
                        {
                            "widget_type": "FEATURE_ROW",
                            "data": {
                                "@type": "type.googleapis.com/widgets.FeatureRowData",
                                "title": "گرمایش شوفاژ",
                                "has_divider": true,
                                "icon": {
                                    "image_url_dark": "https://s100.divarcdn.com/static/imgs/widget-icons/dark/icon_secondary/sunny.png",
                                    "image_url_light": "https://s100.divarcdn.com/static/imgs/widget-icons/light/icon_secondary/sunny.png",
                                    "icon_name": "SUNNY",
                                    "icon_color": "ICON_SECONDARY"
                                },
                                "image_url": "",
                                "image_color": "UNKNOWN",
                                "disabled": false
                            },
                            "visibility_condition": []
                        },
                        {
                            "widget_type": "FEATURE_ROW",
                            "data": {
                                "@type": "type.googleapis.com/widgets.FeatureRowData",
                                "title": "تأمین‌کننده آب گرم موتورخانه",
                                "icon": {
                                    "image_url_dark": "https://s100.divarcdn.com/static/imgs/widget-icons/dark/icon_secondary/thermometer.png",
                                    "image_url_light": "https://s100.divarcdn.com/static/imgs/widget-icons/light/icon_secondary/thermometer.png",
                                    "icon_name": "THERMOMETER",
                                    "icon_color": "ICON_SECONDARY"
                                },
                                "image_url": "",
                                "image_color": "UNKNOWN",
                                "has_divider": false,
                                "disabled": false
                            },
                            "visibility_condition": []
                        }
                    ],
                    "is_searchable": false,
                    "nav_bar": []
                }
            }
        ],
        "location": {
            "latitude": "35.71929",
            "longitude": "51.412136",
            "map_url": "https://cdn.raah.ir/divar-images-2/QZMQbn3j.png"
        },
        "images": [
            "https://s100.divarcdn.com/static/photo/post/51sffbKKBHHGf-80cn4AWA/5b7b5139-5061-4bb6-9af9-8ada8199bd14.webp",
            "https://s100.divarcdn.com/static/photo/post/ORHpY4XdLlRdgNdGgzmwIA/0c7d3b4a-0370-4daf-8e67-dcf44fd9cb99.webp",
            "https://s100.divarcdn.com/static/photo/post/SJz7SXa6J6kra0Kx4IvUOg/64fc8a7b-53f6-4030-977b-20ea92a306c9.webp",
            "https://s100.divarcdn.com/static/photo/post/j_6W3AhjJi1fVjbVBW9D8g/0087186d-e9f2-4425-8e1e-fafda1024275.webp",
            "https://s100.divarcdn.com/static/photo/post/5YFJ8MLC2RKamu6pu7h_2g/835b0e94-74f2-4d1e-b511-64615ab2acda.webp",
            "https://s100.divarcdn.com/static/photo/post/qUPAgIFTLXzceedYqTZw4Q/325bbc82-b176-4dee-9ae7-a22b77c9e4a6.webp",
            "https://s100.divarcdn.com/static/photo/post/_7m1TurH-OqwtJrM9NhecA/84098672-a380-461b-bffb-d4acdb36a3a3.webp"
        ],
        "web_images": [
            [
                {
                    "src": "https://s100.divarcdn.com/static/photo/post/51sffbKKBHHGf-80cn4AWA/5b7b5139-5061-4bb6-9af9-8ada8199bd14.webp",
                    "type": "image/webp"
                },
                {
                    "src": "https://s100.divarcdn.com/static/photo/post/51sffbKKBHHGf-80cn4AWA/5b7b5139-5061-4bb6-9af9-8ada8199bd14.jpg",
                    "type": "image/jpeg"
                }
            ],
            [
                {
                    "src": "https://s100.divarcdn.com/static/photo/post/ORHpY4XdLlRdgNdGgzmwIA/0c7d3b4a-0370-4daf-8e67-dcf44fd9cb99.webp",
                    "type": "image/webp"
                },
                {
                    "src": "https://s100.divarcdn.com/static/photo/post/ORHpY4XdLlRdgNdGgzmwIA/0c7d3b4a-0370-4daf-8e67-dcf44fd9cb99.jpg",
                    "type": "image/jpeg"
                }
            ],
            [
                {
                    "src": "https://s100.divarcdn.com/static/photo/post/SJz7SXa6J6kra0Kx4IvUOg/64fc8a7b-53f6-4030-977b-20ea92a306c9.webp",
                    "type": "image/webp"
                },
                {
                    "src": "https://s100.divarcdn.com/static/photo/post/SJz7SXa6J6kra0Kx4IvUOg/64fc8a7b-53f6-4030-977b-20ea92a306c9.jpg",
                    "type": "image/jpeg"
                }
            ],
            [
                {
                    "src": "https://s100.divarcdn.com/static/photo/post/j_6W3AhjJi1fVjbVBW9D8g/0087186d-e9f2-4425-8e1e-fafda1024275.webp",
                    "type": "image/webp"
                },
                {
                    "src": "https://s100.divarcdn.com/static/photo/post/j_6W3AhjJi1fVjbVBW9D8g/0087186d-e9f2-4425-8e1e-fafda1024275.jpg",
                    "type": "image/jpeg"
                }
            ],
            [
                {
                    "src": "https://s100.divarcdn.com/static/photo/post/5YFJ8MLC2RKamu6pu7h_2g/835b0e94-74f2-4d1e-b511-64615ab2acda.webp",
                    "type": "image/webp"
                },
                {
                    "src": "https://s100.divarcdn.com/static/photo/post/5YFJ8MLC2RKamu6pu7h_2g/835b0e94-74f2-4d1e-b511-64615ab2acda.jpg",
                    "type": "image/jpeg"
                }
            ],
            [
                {
                    "src": "https://s100.divarcdn.com/static/photo/post/qUPAgIFTLXzceedYqTZw4Q/325bbc82-b176-4dee-9ae7-a22b77c9e4a6.webp",
                    "type": "image/webp"
                },
                {
                    "src": "https://s100.divarcdn.com/static/photo/post/qUPAgIFTLXzceedYqTZw4Q/325bbc82-b176-4dee-9ae7-a22b77c9e4a6.jpg",
                    "type": "image/jpeg"
                }
            ],
            [
                {
                    "src": "https://s100.divarcdn.com/static/photo/post/_7m1TurH-OqwtJrM9NhecA/84098672-a380-461b-bffb-d4acdb36a3a3.webp",
                    "type": "image/webp"
                },
                {
                    "src": "https://s100.divarcdn.com/static/photo/post/_7m1TurH-OqwtJrM9NhecA/84098672-a380-461b-bffb-d4acdb36a3a3.jpg",
                    "type": "image/jpeg"
                }
            ]
        ],
        "breadcrumb": {
            "categories": [
                {
                    "icon_url": "",
                    "old_meta_id": 214,
                    "parent_slug": "residential-rent",
                    "slug": "apartment-rent",
                    "title": "اجارهٔ آپارتمان",
                    "second_slug": "اجارهٔ آپارتمان",
                    "relative_url": "tehran/rent-apartment"
                },
                {
                    "icon_url": "",
                    "old_meta_id": 213,
                    "parent_slug": "real-estate",
                    "slug": "residential-rent",
                    "title": "اجارهٔ مسکونی",
                    "second_slug": "اجارهٔ مسکونی",
                    "relative_url": "tehran/rent-residential"
                },
                {
                    "icon_url": "https://s100.divarcdn.com/static/explorers/categories/house_%s.png",
                    "old_meta_id": 143,
                    "parent_slug": "root",
                    "slug": "real-estate",
                    "title": "املاک",
                    "second_slug": "املاک",
                    "relative_url": "tehran/real-estate"
                },
                {
                    "icon_url": "",
                    "old_meta_id": 0,
                    "parent_slug": null,
                    "slug": "root",
                    "title": "همه آگهی ها",
                    "second_slug": "همه آگهی ها",
                    "relative_url": "tehran"
                }
            ],
            "main_url": "اجارهٔ-مسکونی/املاک/اجارهٔ-آپارتمان/",
            "base_url": "https://divar.ir/tehran/تهران/browse"
        },
        "contact": {
            "phone": "0991901xxxx",
            "ab_mode": 2,
            "chat": true
        },
        "links": [
            {
                "title": "اجارهٔ آپارتمان",
                "url": "https://divar.ir/tehran/تهران/browse/?query=0,اجارهٔ-آپارتمان",
                "relative_url": "tehran/rent-apartment"
            },
            {
                "title": "اجارهٔ آپارتمان در بهجت‌آباد",
                "url": "https://divar.ir/tehran/تهران/بهجت‌آباد/browse/اجارهٔ-مسکونی/املاک/اجارهٔ-آپارتمان/?place=8,297",
                "relative_url": "tehran/rent-apartment/behjat-abad"
            }
        ],
        "messages": [],
        "warnings": [
            {
                "title": "راهنمای خرید امن",
                "link": "https://divar.ir/__safety_notice/"
            }
        ],
        "car_inspection": null,
        "tags": [],
        "customer_car_inspection_request": null,
        "suggestions": {
            "suggestion_available": false,
            "title": "",
            "posts": [],
            "widget_list": [],
            "post_suggestion_extra_logs": []
        },
        "note": {
            "enable": true
        }
    },
    "token": "QZMQbn3j",
    "error": 0
}