{
    "data": {
        "nabz_product_id": null,
        "business_card_slug": null,
        "seo": {
            "title": "۴۵متری مجردی زوج_ سبلان لشکر حیدری نوروزی فرد|اجارهٔ آپارتمان|تهران، سبلان|دیوار",
            "description": "۴۵متری مجردی زوج_ سبلان لشکر حیدری نوروزی فرد|اجارهٔ آپارتمان|تهران، سبلان|خرید و فروش با سلام\n\nطبقه اول\nبدون تبدیل\nتخلیه فوری\n\nدسترسی مترو سبلان و صیاد و بی آر تی\nاتوبان های صیاد و امام علی\n\nبرای هماهنگی بازدید لطفا فقط تماس بگیرید.| سایت ثبت آگهی، نیازمندی و خرید و فروش دیوار",
            "url": "https://divar.ir/v/%DB%B4%DB%B5%D9%85%D8%AA%D8%B1%DB%8C-%D9%85%D8%AC%D8%B1%D8%AF%DB%8C-%D8%B2%D9%88%D8%AC-%D8%B3%D8%A8%D9%84%D8%A7%D9%86-%D9%84%D8%B4%DA%A9%D8%B1-%D8%AD%DB%8C%D8%AF%D8%B1%DB%8C-%D9%86%D9%88%D8%B1%D9%88%D8%B2%DB%8C-%D9%81%D8%B1%D8%AF_اجارهٔ-آپارتمان_تهران_سبلان_دیوار/QZz0ou3c",
            "home_url": "https://divar.ir/tehran/تهران/browse",
            "android_package_name": "ir.divar",
            "ios_app_id": "863029557",
            "android_app_url": "android-app://ir.divar/http/v/۴۵متری مجردی زوج_ سبلان لشکر حیدری نوروزی فرد/QZz0ou3c/",
            "ios_app_url": "ios-app://863029557/http/v/۴۵متری مجردی زوج_ سبلان لشکر حیدری نوروزی فرد/QZz0ou3c/",
            "thumbnail": "https://s100.divarcdn.com/static/photo/thumbnail/A5MdGHyxNCt8xbP7PsIytw/fc291166-32d6-41ce-ac49-2f6a88591cf9.jpg"
        },
        "share": {
            "title": "۴۵متری مجردی زوج_ سبلان لشکر حیدری نوروزی فرد",
            "description": "با سلام\n\nطبقه اول\nبدون تبدیل\nتخلیه فوری\n\nدسترسی مترو سبلان و صیاد و بی آر تی\nاتوبان های صیاد و امام علی\n\nبرای هماهنگی بازدید لطفا فقط تماس بگیرید.",
            "android_url": "https://divar.ir/v/QZz0ou3c?ref=android",
            "ios_url": "https://divar.ir/v/QZz0ou3c?ref=ios",
            "web_url": "https://divar.ir/v/QZz0ou3c"
        },
        "url": "https://divar.ir/v/%DB%B4%DB%B5%D9%85%D8%AA%D8%B1%DB%8C-%D9%85%D8%AC%D8%B1%D8%AF%DB%8C-%D8%B2%D9%88%D8%AC-%D8%B3%D8%A8%D9%84%D8%A7%D9%86-%D9%84%D8%B4%DA%A9%D8%B1-%D8%AD%DB%8C%D8%AF%D8%B1%DB%8C-%D9%86%D9%88%D8%B1%D9%88%D8%B2%DB%8C-%D9%81%D8%B1%D8%AF_اجارهٔ-آپارتمان_تهران_سبلان_دیوار/QZz0ou3c",
        "category": {
            "slug": "apartment-rent",
            "title": "اجارهٔ آپارتمان",
            "second_slug": "اجارهٔ آپارتمان"
        },
        "description": "با سلام\n\nطبقه اول\nبدون تبدیل\nتخلیه فوری\n\nدسترسی مترو سبلان و صیاد و بی آر تی\nاتوبان های صیاد و امام علی\n\nبرای هماهنگی بازدید لطفا فقط تماس بگیرید.",
        "business_data": {
            "business_type": "real-estate-business",
            "business_ref": "11167",
            "data": {
                "id": "11167",
                "name": "گروه املاک احسان",
                "slug": "cguZn0v6",
                "score": 0.67676693,
                "address": "میدان سبلان ابتدای گلبرگ غربی ابتدای خیابان حیدری پلاک ۴۳۲",
                "agentInfo": {
                    "name": "~ عرفان رحمانی ~",
                    "slug": "OVUzBVwL"
                },
                "submitType": "AGENCY_SUBMIT",
                "shortAddress": "تهران، سبلان",
                "telephoneNumber": "02188410878"
            }
        },
        "city": "تهران",
        "webengage": {
            "category": "apartment-rent",
            "token": "QZz0ou3c",
            "city": "tehran",
            "brand_model": null,
            "image_count": 7,
            "district": "سبلان",
            "cat_3": {
                "full_title": "اجاره آپارتمان",
                "icon_url": "",
                "old_meta_id": 214,
                "parent_slug": "residential-rent",
                "slug": "apartment-rent",
                "title": "اجارهٔ آپارتمان",
                "second_slug": "اجارهٔ آپارتمان",
                "relative_url": "tehran/rent-apartment"
            },
            "cat_2": {
                "full_title": "",
                "icon_url": "",
                "old_meta_id": 213,
                "parent_slug": "real-estate",
                "slug": "residential-rent",
                "title": "اجارهٔ مسکونی",
                "second_slug": "اجارهٔ مسکونی",
                "relative_url": "tehran/rent-residential"
            },
            "cat_1": {
                "full_title": "",
                "icon_url": "https://s100.divarcdn.com/static/explorers/categories/house_%s.png",
                "old_meta_id": 143,
                "parent_slug": "root",
                "slug": "real-estate",
                "title": "املاک",
                "second_slug": "املاک",
                "relative_url": "tehran/real-estate"
            },
            "status": "",
            "originality": "",
            "business_type": "real-estate-business",
            "business_ref": "11167",
            "data": {
                "id": "11167",
                "name": "گروه املاک احسان",
                "slug": "cguZn0v6",
                "score": 0.67676693,
                "address": "میدان سبلان ابتدای گلبرگ غربی ابتدای خیابان حیدری پلاک ۴۳۲",
                "agentInfo": {
                    "name": "~ عرفان رحمانی ~",
                    "slug": "OVUzBVwL"
                },
                "submitType": "AGENCY_SUBMIT",
                "shortAddress": "تهران، سبلان",
                "telephoneNumber": "02188410878"
            },
            "price": null,
            "rent": 6000000,
            "credit": 80000000
        },
        "district": "سبلان",
        "brand_model": null
    },
    "widgets": {
        "header": {
            "date": "پریروز",
            "subtitle": "پریروز در تهران، سبلان | اجاره آپارتمان",
            "title": "۴۵متری مجردی زوج/ سبلان لشکر حیدری نوروزی فرد",
            "thumbnail": "https://s100.divarcdn.com/static/photo/thumbnail/A5MdGHyxNCt8xbP7PsIytw/fc291166-32d6-41ce-ac49-2f6a88591cf9.jpg",
            "place": "سبلان",
            "business_logo": null
        },
        "description": "با سلام\n\nطبقه اول\nبدون تبدیل\nتخلیه فوری\n\nدسترسی مترو سبلان و صیاد و بی آر تی\nاتوبان های صیاد و امام علی\n\nبرای هماهنگی بازدید لطفا فقط تماس بگیرید.",
        "description_show_lines": 0,
        "list_data": [
            {
                "format": "group_info_row",
                "title": "اطلاعات",
                "has_divider": true,
                "items": [
                    {
                        "title": "متراژ",
                        "value": "۴۵"
                    },
                    {
                        "title": "ساخت",
                        "value": "۱۳۸۰"
                    },
                    {
                        "title": "اتاق",
                        "value": "۱"
                    }
                ]
            },
            {
                "title": "ودیعه",
                "format": "string",
                "value": "۸۰٬۰۰۰٬۰۰۰ تومان"
            },
            {
                "title": "اجارهٔ ماهانه",
                "format": "string",
                "value": "۶٬۰۰۰٬۰۰۰ تومان"
            },
            {
                "title": "ودیعه و اجاره",
                "format": "string",
                "value": "غیر قابل تبدیل"
            },
            {
                "title": "مناسب برای",
                "format": "string",
                "value": "خانواده و مجرد"
            },
            {
                "title": "آژانس املاک",
                "value": "گروه املاک احسان",
                "format": "string"
            },
            {
                "title": "طبقه",
                "format": "string",
                "value": "۱ از ۲"
            },
            {
                "format": "group_feature_row",
                "title": "ویژگی‌ها و امکانات",
                "items": [
                    {
                        "title": "آسانسور ندارد",
                        "available": false,
                        "icon": {
                            "image_url_dark": "https://s100.divarcdn.com/static/imgs/widget-icons/dark/icon_hint/elevator.png",
                            "image_url_light": "https://s100.divarcdn.com/static/imgs/widget-icons/light/icon_hint/elevator.png",
                            "icon_name": "ELEVATOR",
                            "icon_color": "ICON_HINT"
                        }
                    },
                    {
                        "title": "پارکینگ ندارد",
                        "available": false,
                        "icon": {
                            "image_url_dark": "https://s100.divarcdn.com/static/imgs/widget-icons/dark/icon_hint/parking.png",
                            "image_url_light": "https://s100.divarcdn.com/static/imgs/widget-icons/light/icon_hint/parking.png",
                            "icon_name": "PARKING",
                            "icon_color": "ICON_HINT"
                        }
                    },
                    {
                        "title": "انباری ندارد",
                        "available": false,
                        "icon": {
                            "image_url_dark": "https://s100.divarcdn.com/static/imgs/widget-icons/dark/icon_hint/cabinet.png",
                            "image_url_light": "https://s100.divarcdn.com/static/imgs/widget-icons/light/icon_hint/cabinet.png",
                            "icon_name": "CABINET",
                            "icon_color": "ICON_HINT"
                        }
                    }
                ],
                "has_divider": true,
                "next_page_text": "نمایش همهٔ جزئیات",
                "next_page": {
                    "title": "ویژگی‌ها و امکانات",
                    "widget_list": [
                        {
                            "widget_type": "TITLE_ROW",
                            "data": {
                                "@type": "type.googleapis.com/widgets.TitleRowData",
                                "text": "ویژگی‌ها",
                                "text_color": "TEXT_PRIMARY",
                                "has_divider": false,
                                "color": ""
                            },
                            "visibility_condition": []
                        },
                        {
                            "widget_type": "UNEXPANDABLE_ROW",
                            "data": {
                                "@type": "type.googleapis.com/widgets.UnexpandableRowData",
                                "title": "تعداد واحد در طبقه",
                                "value": "۱",
                                "has_divider": true,
                                "compact": false,
                                "has_copy_to_clipboard": false
                            },
                            "visibility_condition": []
                        },
                        {
                            "widget_type": "UNEXPANDABLE_ROW",
                            "data": {
                                "@type": "type.googleapis.com/widgets.UnexpandableRowData",
                                "title": "جهت ساختمان",
                                "value": "شمالی",
                                "has_divider": true,
                                "compact": false,
                                "has_copy_to_clipboard": false
                            },
                            "visibility_condition": []
                        },
                        {
                            "widget_type": "TITLE_ROW",
                            "data": {
                                "@type": "type.googleapis.com/widgets.TitleRowData",
                                "text": "امکانات",
                                "text_color": "TEXT_PRIMARY",
                                "has_divider": false,
                                "color": ""
                            },
                            "visibility_condition": []
                        },
                        {
                            "widget_type": "FEATURE_ROW",
                            "data": {
                                "@type": "type.googleapis.com/widgets.FeatureRowData",
                                "title": "آسانسور ندارد",
                                "has_divider": true,
                                "icon": {
                                    "image_url_dark": "https://s100.divarcdn.com/static/imgs/widget-icons/dark/icon_secondary/elevator.png",
                                    "image_url_light": "https://s100.divarcdn.com/static/imgs/widget-icons/light/icon_secondary/elevator.png",
                                    "icon_name": "ELEVATOR",
                                    "icon_color": "ICON_SECONDARY"
                                },
                                "image_url": "",
                                "image_color": "UNKNOWN",
                                "disabled": false
                            },
                            "visibility_condition": []
                        },
                        {
                            "widget_type": "FEATURE_ROW",
                            "data": {
                                "@type": "type.googleapis.com/widgets.FeatureRowData",
                                "title": "پارکینگ ندارد",
                                "has_divider": true,
                                "icon": {
                                    "image_url_dark": "https://s100.divarcdn.com/static/imgs/widget-icons/dark/icon_secondary/parking.png",
                                    "image_url_light": "https://s100.divarcdn.com/static/imgs/widget-icons/light/icon_secondary/parking.png",
                                    "icon_name": "PARKING",
                                    "icon_color": "ICON_SECONDARY"
                                },
                                "image_url": "",
                                "image_color": "UNKNOWN",
                                "disabled": false
                            },
                            "visibility_condition": []
                        },
                        {
                            "widget_type": "FEATURE_ROW",
                            "data": {
                                "@type": "type.googleapis.com/widgets.FeatureRowData",
                                "title": "انباری ندارد",
                                "has_divider": true,
                                "icon": {
                                    "image_url_dark": "https://s100.divarcdn.com/static/imgs/widget-icons/dark/icon_secondary/cabinet.png",
                                    "image_url_light": "https://s100.divarcdn.com/static/imgs/widget-icons/light/icon_secondary/cabinet.png",
                                    "icon_name": "CABINET",
                                    "icon_color": "ICON_SECONDARY"
                                },
                                "image_url": "",
                                "image_color": "UNKNOWN",
                                "disabled": false
                            },
                            "visibility_condition": []
                        },
                        {
                            "widget_type": "FEATURE_ROW",
                            "data": {
                                "@type": "type.googleapis.com/widgets.FeatureRowData",
                                "title": "بالکن ندارد",
                                "has_divider": true,
                                "icon": {
                                    "image_url_dark": "https://s100.divarcdn.com/static/imgs/widget-icons/dark/icon_secondary/balcony.png",
                                    "image_url_light": "https://s100.divarcdn.com/static/imgs/widget-icons/light/icon_secondary/balcony.png",
                                    "icon_name": "BALCONY",
                                    "icon_color": "ICON_SECONDARY"
                                },
                                "image_url": "",
                                "image_color": "UNKNOWN",
                                "disabled": false
                            },
                            "visibility_condition": []
                        },
                        {
                            "widget_type": "FEATURE_ROW",
                            "data": {
                                "@type": "type.googleapis.com/widgets.FeatureRowData",
                                "title": "جنس کف موکت",
                                "has_divider": true,
                                "icon": {
                                    "image_url_dark": "https://s100.divarcdn.com/static/imgs/widget-icons/dark/icon_secondary/texture.png",
                                    "image_url_light": "https://s100.divarcdn.com/static/imgs/widget-icons/light/icon_secondary/texture.png",
                                    "icon_name": "TEXTURE",
                                    "icon_color": "ICON_SECONDARY"
                                },
                                "image_url": "",
                                "image_color": "UNKNOWN",
                                "disabled": false
                            },
                            "visibility_condition": []
                        },
                        {
                            "widget_type": "FEATURE_ROW",
                            "data": {
                                "@type": "type.googleapis.com/widgets.FeatureRowData",
                                "title": "سرویس بهداشتی ایرانی",
                                "has_divider": true,
                                "icon": {
                                    "image_url_dark": "https://s100.divarcdn.com/static/imgs/widget-icons/dark/icon_secondary/wc.png",
                                    "image_url_light": "https://s100.divarcdn.com/static/imgs/widget-icons/light/icon_secondary/wc.png",
                                    "icon_name": "WC",
                                    "icon_color": "ICON_SECONDARY"
                                },
                                "image_url": "",
                                "image_color": "UNKNOWN",
                                "disabled": false
                            },
                            "visibility_condition": []
                        },
                        {
                            "widget_type": "FEATURE_ROW",
                            "data": {
                                "@type": "type.googleapis.com/widgets.FeatureRowData",
                                "title": "سرمایش کولر آبی",
                                "has_divider": true,
                                "icon": {
                                    "image_url_dark": "https://s100.divarcdn.com/static/imgs/widget-icons/dark/icon_secondary/snowflake.png",
                                    "image_url_light": "https://s100.divarcdn.com/static/imgs/widget-icons/light/icon_secondary/snowflake.png",
                                    "icon_name": "SNOWFLAKE",
                                    "icon_color": "ICON_SECONDARY"
                                },
                                "image_url": "",
                                "image_color": "UNKNOWN",
                                "disabled": false
                            },
                            "visibility_condition": []
                        },
                        {
                            "widget_type": "FEATURE_ROW",
                            "data": {
                                "@type": "type.googleapis.com/widgets.FeatureRowData",
                                "title": "گرمایش بخاری",
                                "has_divider": true,
                                "icon": {
                                    "image_url_dark": "https://s100.divarcdn.com/static/imgs/widget-icons/dark/icon_secondary/sunny.png",
                                    "image_url_light": "https://s100.divarcdn.com/static/imgs/widget-icons/light/icon_secondary/sunny.png",
                                    "icon_name": "SUNNY",
                                    "icon_color": "ICON_SECONDARY"
                                },
                                "image_url": "",
                                "image_color": "UNKNOWN",
                                "disabled": false
                            },
                            "visibility_condition": []
                        },
                        {
                            "widget_type": "FEATURE_ROW",
                            "data": {
                                "@type": "type.googleapis.com/widgets.FeatureRowData",
                                "title": "تأمین‌کننده آب گرم آبگرم‌کن",
                                "icon": {
                                    "image_url_dark": "https://s100.divarcdn.com/static/imgs/widget-icons/dark/icon_secondary/thermometer.png",
                                    "image_url_light": "https://s100.divarcdn.com/static/imgs/widget-icons/light/icon_secondary/thermometer.png",
                                    "icon_name": "THERMOMETER",
                                    "icon_color": "ICON_SECONDARY"
                                },
                                "image_url": "",
                                "image_color": "UNKNOWN",
                                "has_divider": false,
                                "disabled": false
                            },
                            "visibility_condition": []
                        }
                    ],
                    "is_searchable": false,
                    "nav_bar": []
                }
            }
        ],
        "location": {
            "latitude": "35.726707",
            "longitude": "51.46518",
            "map_url": "https://cdn.raah.ir/divar-images-2/QZz0ou3c.png"
        },
        "images": [
            "https://s100.divarcdn.com/static/photo/post/s2EXcZrAP4C-zq3yB7FP5A/922a68ee-023b-4362-bd31-e6ee354c8ed7.webp",
            "https://s100.divarcdn.com/static/photo/post/ynu2pdtgIDK3VpC7OJjuMg/0207b38c-a5dd-4850-9683-2ae62319771c.webp",
            "https://s100.divarcdn.com/static/photo/post/hInb1v9Jz9X1AOnax629kQ/0e988b44-ff64-4502-88d8-53e61907c3e9.webp",
            "https://s100.divarcdn.com/static/photo/post/PFnrTS6Wx8MQ7SmAzpwuUg/203d5b60-c9da-41b6-87a1-cf4480d71d59.webp",
            "https://s100.divarcdn.com/static/photo/post/ckFDJAm9yIwZDA0Pb97Zcg/e093eaa6-dea0-47ed-9883-d3f597c2c3fe.webp",
            "https://s100.divarcdn.com/static/photo/post/9PnT8BdKl5fo83jAD3-8_A/1e5f179b-28da-44a2-bd94-b28487a09477.webp",
            "https://s100.divarcdn.com/static/photo/post/8O4XWrhoPnW9fRIrd_YyPg/fc291166-32d6-41ce-ac49-2f6a88591cf9.webp"
        ],
        "web_images": [
            [
                {
                    "src": "https://s100.divarcdn.com/static/photo/post/s2EXcZrAP4C-zq3yB7FP5A/922a68ee-023b-4362-bd31-e6ee354c8ed7.webp",
                    "type": "image/webp"
                },
                {
                    "src": "https://s100.divarcdn.com/static/photo/post/s2EXcZrAP4C-zq3yB7FP5A/922a68ee-023b-4362-bd31-e6ee354c8ed7.jpg",
                    "type": "image/jpeg"
                }
            ],
            [
                {
                    "src": "https://s100.divarcdn.com/static/photo/post/ynu2pdtgIDK3VpC7OJjuMg/0207b38c-a5dd-4850-9683-2ae62319771c.webp",
                    "type": "image/webp"
                },
                {
                    "src": "https://s100.divarcdn.com/static/photo/post/ynu2pdtgIDK3VpC7OJjuMg/0207b38c-a5dd-4850-9683-2ae62319771c.jpg",
                    "type": "image/jpeg"
                }
            ],
            [
                {
                    "src": "https://s100.divarcdn.com/static/photo/post/hInb1v9Jz9X1AOnax629kQ/0e988b44-ff64-4502-88d8-53e61907c3e9.webp",
                    "type": "image/webp"
                },
                {
                    "src": "https://s100.divarcdn.com/static/photo/post/hInb1v9Jz9X1AOnax629kQ/0e988b44-ff64-4502-88d8-53e61907c3e9.jpg",
                    "type": "image/jpeg"
                }
            ],
            [
                {
                    "src": "https://s100.divarcdn.com/static/photo/post/PFnrTS6Wx8MQ7SmAzpwuUg/203d5b60-c9da-41b6-87a1-cf4480d71d59.webp",
                    "type": "image/webp"
                },
                {
                    "src": "https://s100.divarcdn.com/static/photo/post/PFnrTS6Wx8MQ7SmAzpwuUg/203d5b60-c9da-41b6-87a1-cf4480d71d59.jpg",
                    "type": "image/jpeg"
                }
            ],
            [
                {
                    "src": "https://s100.divarcdn.com/static/photo/post/ckFDJAm9yIwZDA0Pb97Zcg/e093eaa6-dea0-47ed-9883-d3f597c2c3fe.webp",
                    "type": "image/webp"
                },
                {
                    "src": "https://s100.divarcdn.com/static/photo/post/ckFDJAm9yIwZDA0Pb97Zcg/e093eaa6-dea0-47ed-9883-d3f597c2c3fe.jpg",
                    "type": "image/jpeg"
                }
            ],
            [
                {
                    "src": "https://s100.divarcdn.com/static/photo/post/9PnT8BdKl5fo83jAD3-8_A/1e5f179b-28da-44a2-bd94-b28487a09477.webp",
                    "type": "image/webp"
                },
                {
                    "src": "https://s100.divarcdn.com/static/photo/post/9PnT8BdKl5fo83jAD3-8_A/1e5f179b-28da-44a2-bd94-b28487a09477.jpg",
                    "type": "image/jpeg"
                }
            ],
            [
                {
                    "src": "https://s100.divarcdn.com/static/photo/post/8O4XWrhoPnW9fRIrd_YyPg/fc291166-32d6-41ce-ac49-2f6a88591cf9.webp",
                    "type": "image/webp"
                },
                {
                    "src": "https://s100.divarcdn.com/static/photo/post/8O4XWrhoPnW9fRIrd_YyPg/fc291166-32d6-41ce-ac49-2f6a88591cf9.jpg",
                    "type": "image/jpeg"
                }
            ]
        ],
        "breadcrumb": {
            "categories": [
                {
                    "icon_url": "",
                    "old_meta_id": 214,
                    "parent_slug": "residential-rent",
                    "slug": "apartment-rent",
                    "title": "اجارهٔ آپارتمان",
                    "second_slug": "اجارهٔ آپارتمان",
                    "relative_url": "tehran/rent-apartment"
                },
                {
                    "icon_url": "",
                    "old_meta_id": 213,
                    "parent_slug": "real-estate",
                    "slug": "residential-rent",
                    "title": "اجارهٔ مسکونی",
                    "second_slug": "اجارهٔ مسکونی",
                    "relative_url": "tehran/rent-residential"
                },
                {
                    "icon_url": "https://s100.divarcdn.com/static/explorers/categories/house_%s.png",
                    "old_meta_id": 143,
                    "parent_slug": "root",
                    "slug": "real-estate",
                    "title": "املاک",
                    "second_slug": "املاک",
                    "relative_url": "tehran/real-estate"
                },
                {
                    "icon_url": "",
                    "old_meta_id": 0,
                    "parent_slug": null,
                    "slug": "root",
                    "title": "همه آگهی ها",
                    "second_slug": "همه آگهی ها",
                    "relative_url": "tehran"
                }
            ],
            "main_url": "اجارهٔ-مسکونی/املاک/اجارهٔ-آپارتمان/",
            "base_url": "https://divar.ir/tehran/تهران/browse"
        },
        "contact": {
            "phone": "0936970xxxx",
            "ab_mode": 2,
            "chat": true
        },
        "links": [
            {
                "title": "اجارهٔ آپارتمان",
                "url": "https://divar.ir/tehran/تهران/browse/?query=0,اجارهٔ-آپارتمان",
                "relative_url": "tehran/rent-apartment"
            },
            {
                "title": "اجارهٔ آپارتمان در سبلان",
                "url": "https://divar.ir/tehran/تهران/سبلان/browse/اجارهٔ-مسکونی/املاک/اجارهٔ-آپارتمان/?place=8,950",
                "relative_url": "tehran/rent-apartment/sabalan"
            }
        ],
        "messages": [],
        "warnings": [
            {
                "title": "راهنمای خرید امن",
                "link": "https://divar.ir/__safety_notice/"
            }
        ],
        "car_inspection": null,
        "tags": [],
        "customer_car_inspection_request": null,
        "suggestions": {
            "suggestion_available": false,
            "title": "",
            "posts": [],
            "widget_list": [],
            "post_suggestion_extra_logs": []
        },
        "note": {
            "enable": true
        }
    },
    "token": "QZz0ou3c",
    "error": 0
}